odoo/addons/l10n_us_partner_legal_number/README.rst
odoo/addons/l10n_us_partner_legal_number/__init__.py
odoo/addons/l10n_us_partner_legal_number/__manifest__.py
odoo/addons/l10n_us_partner_legal_number/i18n/l10n_us_partner_legal_number.pot
odoo/addons/l10n_us_partner_legal_number/models/__init__.py
odoo/addons/l10n_us_partner_legal_number/models/base.py
odoo/addons/l10n_us_partner_legal_number/models/res_partner.py
odoo/addons/l10n_us_partner_legal_number/static/description/icon.png
odoo/addons/l10n_us_partner_legal_number/views/res_partner.xml
odoo14_addon_l10n_us_partner_legal_number-14.0.1.0.1.dist-info/METADATA
odoo14_addon_l10n_us_partner_legal_number-14.0.1.0.1.dist-info/WHEEL
odoo14_addon_l10n_us_partner_legal_number-14.0.1.0.1.dist-info/top_level.txt
odoo14_addon_l10n_us_partner_legal_number-14.0.1.0.1.dist-info/RECORD
